<annotation verified="no">
  <folder>&#22270;&#29255;&#20219;&#21153;&#32452;_20170515_2043</folder>
  <filename>2143d76df7424bd483bf4e934c45c7c9</filename>
  <path>E:\Desktop\&#22270;&#29255;&#20219;&#21153;&#32452;_20170515_2043\2143d76df7424bd483bf4e934c45c7c9.png</path>
  <source>
    <database>Unknown</database>
  </source>
  <size>
    <width>0</width>
    <height>0</height>
    <depth>3</depth>
  </size>
  <segmented>0</segmented>
  <object>
    <name>14.DetectArea</name>
    <pose>Unspecified</pose>
    <truncated>0</truncated>
    <difficult>0</difficult>
    <bndbox>
      <xmin>10</xmin>
      <ymin>438</ymin>
      <xmax>719</xmax>
      <ymax>992</ymax>
    </bndbox>
  </object>
</annotation>
